ln_qt/__init__.py
ln_qt/annotate_ui_button.py
ln_qt/print_data.py
ln_qt/print_elapsed_time.py
ln_qt/print_pipeline_status.py
ln_qt/print_shape.py
ln_qt-1.0.2.dist-info/licenses/AUTHORS.rst
ln_qt-1.0.2.dist-info/licenses/LICENSE
ln_qt-1.0.2.dist-info/METADATA
ln_qt-1.0.2.dist-info/WHEEL
ln_qt-1.0.2.dist-info/entry_points.txt
ln_qt-1.0.2.dist-info/top_level.txt
ln_qt-1.0.2.dist-info/zip-safe
ln_qt-1.0.2.dist-info/RECORD
