Metadata-Version: 2.4
Name: LN-Qt
Version: 1.0.2
Summary: LiveNodes: node based live streaming sensor/data and visualization suite.
Author-email: Yale Hartmann <yale.hartmann@uni-bremen.de>
License:                     GNU GENERAL PUBLIC LICENSE
License-File: LICENSE
License-File: AUTHORS.rst
Requires-Dist: livenodes>=0.12.1b1
Requires-Dist: ln_ports>=0.12.1b1
Requires-Dist: numpy>=1.22.1
Requires-Dist: PyQt5>=5.12.3
Provides-Extra: dev
Requires-Dist: tox; extra == "dev"
Requires-Dist: pytest>=7.0.1; extra == "dev"
Dynamic: license-file
